junmook_test/test1.py
junmook_test/test2.py
junmook_test-0.0.0.2.dist-info/METADATA
junmook_test-0.0.0.2.dist-info/WHEEL
junmook_test-0.0.0.2.dist-info/top_level.txt
junmook_test-0.0.0.2.dist-info/RECORD
